rewardanything/__init__.py
rewardanything/cli.py
rewardanything/client.py
rewardanything/local.py
rewardanything/models.py
rewardanything/processing.py
rewardanything/serve.py
rewardanything/utils.py
rewardanything-1.0.1.dist-info/licenses/LICENSE
rewardanything-1.0.1.dist-info/METADATA
rewardanything-1.0.1.dist-info/WHEEL
rewardanything-1.0.1.dist-info/entry_points.txt
rewardanything-1.0.1.dist-info/top_level.txt
rewardanything-1.0.1.dist-info/RECORD
