Metadata-Version: 2.4
Name: rewardanything
Version: 1.0.1
Summary: RewardAnything: Generalizable Principle-Following Reward Models
Home-page: https://github.com/zhuohaoyu/RewardAnything
Author: Jiali Zeng, Weizheng Gu, Yidong Wang, Jindong Wang, Fandong Meng, Jie Zhou, Yue Zhang, Shikun Zhang, Wei Ye
Author-email: Zhuohao Yu <zhuohaoyu1228@gmail.com>
Maintainer-email: Zhuohao Yu <zhuohaoyu1228@gmail.com>
License: Apache-2.0
Project-URL: Homepage, https://github.com/zhuohaoyu/RewardAnything
Project-URL: Repository, https://github.com/zhuohaoyu/RewardAnything
Project-URL: Documentation, https://github.com/zhuohaoyu/RewardAnything#readme
Project-URL: Bug Tracker, https://github.com/zhuohaoyu/RewardAnything/issues
Keywords: machine learning,reward modeling,RLHF,principle-following,evaluation,LLM,alignment
Classifier: Development Status :: 4 - Beta
Classifier: Intended Audience :: Developers
Classifier: Intended Audience :: Science/Research
Classifier: License :: OSI Approved :: Apache Software License
Classifier: Operating System :: OS Independent
Classifier: Programming Language :: Python :: 3
Classifier: Programming Language :: Python :: 3.8
Classifier: Programming Language :: Python :: 3.9
Classifier: Programming Language :: Python :: 3.10
Classifier: Programming Language :: Python :: 3.11
Classifier: Programming Language :: Python :: 3.12
Classifier: Topic :: Scientific/Engineering :: Artificial Intelligence
Classifier: Topic :: Software Development :: Libraries :: Python Modules
Requires-Python: >=3.8
License-File: LICENSE
Requires-Dist: torch>=2.0.0
Requires-Dist: transformers>=4.51.0
Requires-Dist: fastapi>=0.104.0
Requires-Dist: uvicorn>=0.24.0
Requires-Dist: pydantic>=2.0.0
Requires-Dist: requests>=2.28.0
Requires-Dist: numpy>=1.21.0
Requires-Dist: scipy>=1.7.0
Requires-Dist: tqdm>=4.64.0
Requires-Dist: openai>=1.0.0
Provides-Extra: server
Requires-Dist: fastapi>=0.104.0; extra == "server"
Requires-Dist: uvicorn>=0.24.0; extra == "server"
Provides-Extra: local
Requires-Dist: torch>=2.0.0; extra == "local"
Requires-Dist: transformers>=4.51.0; extra == "local"
Provides-Extra: all
Requires-Dist: fastapi>=0.104.0; extra == "all"
Requires-Dist: uvicorn>=0.24.0; extra == "all"
Requires-Dist: torch>=2.0.0; extra == "all"
Requires-Dist: transformers>=4.51.0; extra == "all"
Provides-Extra: dev
Requires-Dist: pytest>=7.0.0; extra == "dev"
Requires-Dist: pytest-asyncio>=0.21.0; extra == "dev"
Requires-Dist: black>=23.0.0; extra == "dev"
Requires-Dist: isort>=5.12.0; extra == "dev"
Requires-Dist: flake8>=6.0.0; extra == "dev"
Requires-Dist: mypy>=1.0.0; extra == "dev"
Dynamic: home-page
Dynamic: license-file
Dynamic: requires-python
